examples/__init__.py
examples/benchmark_custom_lmgec.py
examples/compare_methods.py
examples/evaluate_with_metrics.py
examples/prepare_custom_dataset.py
examples/tune_hyperparams.py
examples/visualize_clusters.py
mvcluster/__init__.py
mvcluster/benchmark/__init__.py
mvcluster/benchmark/lmgec_benchmark.py
mvcluster/cluster/__init__.py
mvcluster/cluster/base.py
mvcluster/cluster/lmgec.py
mvcluster/cluster/lmgec_v2.py
mvcluster/models/__init__.py
mvcluster/models/lmgec_core.py
mvcluster/prepared_datasets/__init__.py
mvcluster/utils/__init__.py
mvcluster/utils/datagen.py
mvcluster/utils/init_utils.py
mvcluster/utils/metrics.py
mvcluster/utils/plot.py
mvcluster/utils/preprocess.py
mvcluster-1.17.dist-info/METADATA
mvcluster-1.17.dist-info/WHEEL
mvcluster-1.17.dist-info/top_level.txt
mvcluster-1.17.dist-info/RECORD
